{"country":"thailand","country_name":"タイ","flag":"🇹🇭","sims":[{"name":"【タイ eSIM】4G-LTE 高速データ通信 データ無制限 データ通信専用【DTAC キャリア】タイ プリペイド simカード Thailand esim 当日発行可能 (1日間 高速データ)","brand":"PLUG TO GO","type":"eSIM","days":1,"price_min":690,"price_max":690,"asin":"B0D4QM8BY6","voice_call":false,"carrier":"DTAC","data_high":"無制限","data_low":null},{"name":"【esim】タイ simカード【DTAC】4G-LTE 高速データ通信 当日発行可能 データ使い放題 Thailand esim データ通信専用 タイプリペイドSIMカード (3日間 高速データ)","brand":"アーモンド　ＳＩｍ　ｃａｒｄ","type":"eSIM","days":3,"price_min":880,"price_max":880,"asin":"B0CLKGP9H1","voice_call":false,"carrier":"DTAC","data_high":"無制限","data_low":null},{"name":"《正規日本語版》タイ 8日間 5GBデータ通信 プリペイドSIMカード 20分無料電話付 【中国聯通香港 China unicom】※面倒な本人登録・パスポート登録は不要です。","brand":"China unicom中国联通","type":"物理SIM","days":8,"price_min":890,"price_max":890,"asin":"B0CV5FL8YW","data_high":"5GB","data_low":"情報不明"},{"name":"東南アジア4ヵ国周遊SIM 利用期間 8日 データ容量5GB 4Gデータ通信 プリペイドSIM ローミングSIM シンガポール・タイ・マレーシア・ベトナム","brand":"Wise SIM","type":"SIM","days":8,"price_min":980,"price_max":980,"asin":"B0BXT5DZ96","data_high":"5GB","data_low":"情報不明"},{"name":"東南アジア 5ヵ国周遊SIM 利用期間 8日 データ容量5GB 4Gデータ通信 プリペイドSIM ローミングSIM インドネシア・シンガポール・タイ・ベトナム・マレーシア","brand":"Wise SIM","type":"SIM","days":8,"price_min":980,"price_max":980,"asin":"B0CJ4RL7T6","data_high":"5GB","data_low":"情報不明"},{"name":"【Almond eSIM】 タイ esim 7日間 15GB高速データ通信 データ使い放題 当日発行可能 LINEで24時間サポート バンコク プリペイド eSIM Thailand esim sim   (7日間15GB 1枚分)","brand":"bigconnect","type":"eSIM","days":7,"price_min":990,"price_max":990,"asin":"B0CS391HSR","data_high":"無制限","data_low":null},{"name":"AIS NET SIM タイ プリペイドSIM タイSIMカード 利用期間7日間 速度が一定で使い放題 データ通信用SIM ※SIMカード有効期限2026年6月30日まで","brand":"Wise SIM","type":"物理SIM","days":7,"price_min":995,"price_max":995,"asin":"B09RG11K86","carrier":"AIS","data_high":"無制限","data_low":null},{"name":"タイSIM AIS タイプリペイドSIM 利用期間7日間 速度が一定で使い放題 データSIM ※SIMカード有効期限2026年6月30日まで","brand":"Wise SIM","type":"物理SIM","days":7,"price_min":995,"price_max":995,"asin":"B0BZRF12NW","carrier":"AIS","data_high":"無制限","data_low":null},{"name":"AIS タイ eSIM 7日間 (168時間) AIS正規発行 データ通信 使い放題 5G/4G対応 / タイESIM タイ旅行 タイ国内用 ESIM Prepaid esim/タイSIM カード タイプリペイド SIM ※eSIMの為、物理SIMの発送はありません","brand":"Wise SIM","type":"eSIM","days":7,"price_min":1100,"price_max":1100,"asin":"B0CXJ8LMWJ","carrier":"AIS","data_high":"無制限","data_low":null},{"name":"【タイeSIM】利用期間7日間 データ通信 使い放題/タイプリペイドSIM AIS正規発行/急な相談もLINEでOK/タイ ESIM eSIM esim / ※esimの為、物理SIMの発送はありません。タイ SIM タイプリペイドSIM","brand":"Wise SIM","type":"eSIM","days":7,"price_min":1100,"price_max":1100,"asin":"B0DG31QQGY","carrier":"AIS","data_high":"無制限","data_low":null},{"name":"タイesim タイ国内用プリペイドESIM 7日間15GB高速データ通信 当日発行可能 Thailand ESIM (7日間15GB)","brand":"bigconnect","type":"eSIM","days":7,"price_min":1180,"price_max":1180,"asin":"B0C6D2QGJD","data_high":"15GB","data_low":"情報不明"},{"name":"タイ eSIM 5日間 データ通信使い放題 5G/4G対応 当日納品可能 QR簡单設定 緊急利用（Lineまで連絡）mewfi","brand":"mewfi","type":"eSIM","days":5,"price_min":1180,"price_max":1180,"asin":"B0CSJTNJR3","data_high":"無制限","data_low":null},{"name":"タイ eSIM 7日間 | 高速データ使い放題 | データ通信専用 | 24時間以内にQRコード送付 | テザリング・ホットスポット対応 | 5G/4G対応","brand":"TSIM","type":"eSIM","days":7,"price_min":1189,"price_max":1189,"asin":"B0DJW7CP7F","voice_call":false,"data_high":"無制限","data_low":null},{"name":"【タイeSIM】 7日間 (168時間) データ通信無制限 お急ぎの方即日対応(LINE相談受付中) 有効期限 / ご購入日より90日以内 タイSIMカードタイプではありません バンコク","brand":"KLP","type":"eSIM","days":7,"price_min":1250,"price_max":1250,"asin":"B0CSNNF6CB","data_high":"無制限","data_low":null},{"name":"タイ sim card 10日間(240時間) 利用可能 タイ国内用プリペイドSIM 5G 4G高速データ容量50ＧＢ タイ プリペイドSIMカード (TRUEMOVE10日間50GB)","brand":"bigconnect","type":"物理SIM","days":10,"price_min":1280,"price_max":1280,"asin":"B0CGPL8SCW","carrier":"TrueMove H","data_high":"50GB","data_low":"情報不明"},{"name":"【タイ SIM】Turemove 正規品 10日間 高速データ無制限 5G/4G対応 タイ プリペイドSIMカード タイsim 24時間多言語サポート","brand":"PLUG TO GO","type":"物理SIM","days":10,"price_min":1280,"price_max":1280,"asin":"B0CZL8SGFV","data_high":"無制限","data_low":null},{"name":"【タイeSIM】TRUE MOVE/Dtac回線 利用日数10日 データ通信 データ容量50GB/タイプリペイドSIM TRUE MOVE/Dtac/タイ ESIM eSIM esim / ※esimの為、物理SIMの発送はありません。","brand":"Wise SIM","type":"eSIM","days":10,"price_min":1290,"price_max":1290,"asin":"B0DMP18921","carrier":"DTAC","data_high":"50GB","data_low":"情報不明"},{"name":"《正規日本語版》【ローミングSIM】東南アジア・マカオ・ベトナム・シンガポール・タイ・マレーシア・ラオス・インドネシア・フィリピン・カンボジア・スリランカの全10ヵ国 8日間 5GB ※面倒な本人登録・パスポート登録は不要です。このSIMカードは中国ではご利用できません。","brand":"China unicom中国联通","type":"物理SIM","days":8,"price_min":1300,"price_max":1300,"asin":"B07DKH2SF3","data_high":"5GB","data_low":"情報不明"},{"name":"【TRUE MOVE】タイSIM データ容量50GB データ利用期間10日間(240時間) タイ国内用 プリペイドSIM データSIM タイSIM prepaid sim Thailand travel","brand":"Wise SIM","type":"SIM","days":10,"price_min":1350,"price_max":1350,"asin":"B0CZXBHH48","carrier":"TrueMove H","data_high":"50GB","data_low":"情報不明"},{"name":"タイ eSIM 7日間 データ通信使い放題 5G/4G対応 当日納品可能 QR簡单設定 緊急利用（Lineまで連絡）mewfi","brand":"mewfi","type":"eSIM","days":7,"price_min":1380,"price_max":1380,"asin":"B0CSJTMSLV","data_high":"無制限","data_low":null},{"name":"【タイeSIM】 10日間 (240時間) データ通信無制限 お急ぎの方即日対応(LINE相談受付中) 有効期限 / ご購入日より90日以内 タイSIMカードタイプではありません バンコク","brand":"KLP","type":"eSIM","days":10,"price_min":1470,"price_max":1470,"asin":"B0DLPXZT7R","data_high":"無制限","data_low":null},{"name":"タイ eSIM 10日間 データ通信使い放題 5G/4G対応 DTAC回線利用 当日納品可能 QR簡单設定 緊急利用（Lineまで連絡）mewfi","brand":"mewfi","type":"eSIM","days":10,"price_min":1580,"price_max":1580,"asin":"B0CSJTQKVL","carrier":"DTAC","data_high":"無制限","data_low":null},{"name":"【ヨーロッパSIM】8日間 1GB/毎日 DeSiM正規卸 | ヨーロッパ43ヵ国でも利用可能 | LINE相談受付中 | simフリー端末のみ対応 説明書付 イーシム/物理SIM","brand":"DeSiM","type":"eSIM","days":8,"price_min":1680,"price_max":1680,"asin":"B0DJ1J1BS4","data_high":"1GB","data_low":"情報不明"},{"name":"アジア4カ国SIM データ容量15GB 利用期間30日 4Gデータ通信 プリペイドSIM ローミングSIM prepaidSIM 利用可能国：インドネシア・シンガポール・タイ・マレーシア","brand":"Wise SIM","type":"SIM","days":30,"price_min":1800,"price_max":1800,"asin":"B0CYCJ582Y","data_high":"15GB","data_low":"情報不明"},{"name":"【 ヨーロッパ SIMカード 】 ヨーロッパ sim 30日間 高速データ通信 10GB ヨーロッパ esim Orange sim 正規品 （有効期限 : 購入日から60日）","brand":"WorldeSIM","type":"eSIM","days":30,"price_min":1870,"price_max":1870,"asin":"B0D8T9S5B2","data_high":"10GB","data_low":"情報不明"},{"name":"【日本 sim】日本 プリペイドSIM 10GB 大容量 Rakutenキャリア使用 プリペイドSIMカード 日本国内用 SIMカード Prepaid SIM プリペイド データ専用 4GLTE対応 (360日間10GB（楽天回線）)","brand":"bigconnect","type":"物理SIM","days":360,"price_min":1930,"price_max":1930,"asin":"B0D138PK57","voice_call":false,"data_high":"10GB","data_low":"情報不明"},{"name":"【ヨーロッパSIM】6日間 2GB/毎日 DeSiM正規卸 | ヨーロッパ43ヵ国でも利用可能 | LINE相談受付中 | simフリー端末のみ対応 説明書付 イーシム/物理SIM","brand":"DeSiM","type":"eSIM","days":6,"price_min":2080,"price_max":2080,"asin":"B0DJ1LRDD8","data_high":"2GB","data_low":"情報不明"},{"name":"【トルコ eSIM】15日間 5GB（十四泊十五日 コスパ重視） DeSiM正規卸 |LINE相談受付中 | 当日発行可能 |データ通信専用（電話番号なし） simフリー端末のみ対応 説明書付 イーシム","brand":"DeSiM","type":"eSIM","days":15,"price_min":2136,"price_max":2136,"asin":"B0DCSZJRLJ","voice_call":false,"data_high":"5GB","data_low":"情報不明"},{"name":"タイesim タイ国内用プリペイドESIM 30日間10GB高速データ通信 25分間現地通話付き 当日発行可能 Thailand ESIM (30日間10GB+25分間現地通話)","brand":"bigconnect","type":"eSIM","days":30,"price_min":2880,"price_max":2880,"asin":"B0DLJH4ZT5","voice_call":true,"data_high":"10GB","data_low":"情報不明"},{"name":"【タイ eSIM】 高速データ 使い放題 即日発行可能 【DTAC キャリア】 タイ プリペイド simカード プーケット バンコク タイ esim タイsim Thailand eSIM (30日間20GB)","brand":"アーモンド　ＳＩｍ　ｃａｒｄ","type":"eSIM","days":30,"price_min":2990,"price_max":2990,"asin":"B0CXNVNK7V","carrier":"DTAC","data_high":"無制限","data_low":null},{"name":"【東南アジア４カ国 eSIM】7日間 20GB（六泊七日 コスパ重視） DeSiM正規卸 | タイ シンガポール マレーシア インドネシアの4ヵ国 利用可能 |LINE相談受付中 | 当日発行可能 |データ通信専用（電話番号なし） simフリー端末のみ対応 説明書付 イーシム","brand":"DeSiM","type":"eSIM","days":7,"price_min":3570,"price_max":3570,"asin":"B0D6NHVXTY","voice_call":false,"data_high":"20GB","data_low":"情報不明"},{"name":"【ギリシャeSIM】7日間 完全無制限（六泊七日 使い放題） DeSiM正規卸 |LINE相談受付中 | 当日発行可能 |データ通信専用（電話番号なし） simフリー端末のみ対応 説明書付 イーシム","brand":"DeSiM","type":"eSIM","days":7,"price_min":5496,"price_max":5496,"asin":"B0D8TW38CS","voice_call":false,"data_high":"無制限","data_low":null},{"name":"【Docomo回線】365日間100GB 5G/4G/LTE対応 プリペイドSIM リチャージ可 期間延長可 残量確認可 契約不要 日本国内用 データ通信専用 物理SIM 大容量 ピン付き 設定簡単 年中無休 多言語安心サポート sim card japan【DXHUB】","brand":"ＤＸＨＵＢ","type":"物理SIM","days":365,"price_min":15580,"price_max":15580,"asin":"B093WJ26L4","voice_call":false,"data_high":"100GB","data_low":"情報不明","image_url":"https://m.media-amazon.com/images/I/81UO99bjnuL._AC_SY741_.jpg","review_score":5.0,"review_count":832,"sms":false,"network":["LTE"]}]}